[{
    "id": "MLB4063409120",
    "title": "Radiador Renault Kangoo 1.6 2006 A 2014 Com Ar 8200072713",
    "value_name_brand": "Renault",
    "value_name_model": "Modelo não especificado",
    "price": 700,
    "picture_ids": [
        "664705-MLB71823749390_092023",
        "658684-MLB71823700012_092023",
        "662598-MLB71877650877_092023"
    ],
    "permalink": "https://produto.mercadolivre.com.br/MLB-4063409120-radiador-renault-kangoo-16-2006-a-2014-com-ar-8200072713-_JM",
    "category": "radiador",
    "subcategory": [
        "outros"
    ]
},
{
    "id": "MLB3564268963",
    "title": "Farol Lado Esquerdo Gol Voyage Saveiro G6 2013 A 2016.",
    "value_name_brand": "Volkswagen",
    "value_name_model": "Modelo não especificado",
    "price": 700,
    "picture_ids": [
        "693792-MLB73928491063_012024",
        "735212-MLB73828219862_012024",
        "658645-MLB73828150230_012024"
    ],
    "permalink": "https://produto.mercadolivre.com.br/MLB-3564268963-farol-lado-esquerdo-gol-voyage-saveiro-g6-2013-a-2016-_JM",
    "category": "farol",
    "subcategory": [
        "esquerdo"
    ]
},
{
    "id": "MLB3583643991",
    "title": "Capa Do Motor  Fiat Toro Ranch 2022/  Commander Cód.46352576",
    "value_name_brand": "Fiat MOPAR",
    "value_name_model": "Modelo não especificado",
    "price": 700,
    "picture_ids": [
        "817378-MLB74307512927_012024",
        "885182-MLB74307956437_012024",
        "642189-MLB74307522715_012024"
    ],
    "permalink": "https://produto.mercadolivre.com.br/MLB-3583643991-capa-do-motor-fiat-toro-ranch-2022-commander-cod46352576-_JM",
    "category": "motor",
    "subcategory": [
        "outros"
    ]
},
{
    "id": "MLB3610901423",
    "title": "Ponteira Escapamento Hyundai Santa Fé V6 2.7 (sejongu014ie)",
    "value_name_brand": "Huundai",
    "value_name_model": "Modelo não especificado",
    "price": 700,
    "picture_ids": [
        "832944-MLB74830299209_022024",
        "933037-MLB74830426925_022024",
        "697109-MLB74698620220_022024"
    ],
    "permalink": "https://produto.mercadolivre.com.br/MLB-3610901423-ponteira-escapamento-hyundai-santa-fe-v6-27-sejongu014ie-_JM",
    "category": "outros",
    "subcategory": [
        "outros"
    ]
},
{
    "id": "MLB3741196880",
    "title": "Chave De Seta Citröen C4 Pallas Hatch, 2008 A 2013.",
    "value_name_brand": "Citroën",
    "value_name_model": "Modelo não especificado",
    "price": 700,
    "picture_ids": [
        "838414-MLB70108172091_062023",
        "835764-MLB70108172111_062023",
        "605983-MLB70108172121_062023"
    ],
    "permalink": "https://produto.mercadolivre.com.br/MLB-3741196880-chave-de-seta-citroen-c4-pallas-hatch-2008-a-2013-_JM",
    "category": "chave",
    "subcategory": [
        "outros"
    ]
},
{
    "id": "MLB4530921004",
    "title": "Aerofólio Traseiro Subaru Forester Xt 2.0 2015/ Original ",
    "value_name_brand": "Subaru",
    "value_name_model": "Modelo não especificado",
    "price": 700,
    "picture_ids": [
        "969715-MLB75216055761_032024",
        "821264-MLB75216055765_032024",
        "720003-MLB75216035753_032024"
    ],
    "permalink": "https://produto.mercadolivre.com.br/MLB-4530921004-aerofolio-traseiro-subaru-forester-xt-20-2015-original-_JM",
    "category": "outros",
    "subcategory": [
        "traseiro"
    ]
},
{
    "id": "MLB3445440945",
    "title": "Farol Renault Duster 2012/ L. Esquerdo Código 260602191r",
    "value_name_brand": "Duster",
    "value_name_model": "Modelo não especificado",
    "price": 700,
    "picture_ids": [
        "670414-MLB71670678758_092023",
        "836673-MLB71721457177_092023",
        "693783-MLB71670639258_092023"
    ],
    "permalink": "https://produto.mercadolivre.com.br/MLB-3445440945-farol-renault-duster-2012-l-esquerdo-codigo-260602191r-_JM",
    "category": "farol",
    "subcategory": [
        "esquerdo"
    ]
},
{
    "id": "MLB3410713349",
    "title": "Moldura Painel Central Com Difusor De Ar Hyundai I30",
    "value_name_brand": "Hyundai",
    "value_name_model": "I30",
    "price": 700,
    "picture_ids": [
        "669917-MLB71096501913_082023",
        "697659-MLB71058990108_082023",
        "886712-MLB71096404039_082023"
    ],
    "permalink": "https://produto.mercadolivre.com.br/MLB-3410713349-moldura-painel-central-com-difusor-de-ar-hyundai-i30-_JM",
    "category": "painel",
    "subcategory": [
        "outros"
    ]
},
{
    "id": "MLB3546826151",
    "title": "Coxim Motor Jeep Compass Flex 2017/ Cód 00534160110",
    "value_name_brand": "mopar jeep",
    "value_name_model": "Modelo não especificado",
    "price": 700,
    "picture_ids": [
        "841196-MLB73435952828_122023",
        "833349-MLB73435972616_122023",
        "860494-MLB73527630119_122023"
    ],
    "permalink": "https://produto.mercadolivre.com.br/MLB-3546826151-coxim-motor-jeep-compass-flex-2017-cod-00534160110-_JM",
    "category": "motor",
    "subcategory": [
        "outros"
    ]
},
{
    "id": "MLB3624986653",
    "title": "Lanterna Traseira Fiat Doblo  2012/ L.direito Fume C.5202482",
    "value_name_brand": "Fiat",
    "value_name_model": "Modelo não especificado",
    "price": 699,
    "picture_ids": [
        "616810-MLB74990950598_032024",
        "963165-MLB75132047417_032024",
        "992242-MLB75132107331_032024"
    ],
    "permalink": "https://produto.mercadolivre.com.br/MLB-3624986653-lanterna-traseira-fiat-doblo-2012-ldireito-fume-c5202482-_JM",
    "category": "lanterna",
    "subcategory": [
        "direito",
        "traseiro"
    ]
},
{
    "id": "MLB3611964277",
    "title": "Forro Da Tampa Traseira Hyundai Santa Fé (817512w000) 12/18 ",
    "value_name_brand": "Hyundai",
    "value_name_model": "Modelo não especificado",
    "price": 700,
    "picture_ids": [
        "992212-MLB74853113855_032024",
        "717352-MLB74853567743_032024",
        "815540-MLB74853133929_032024"
    ],
    "permalink": "https://produto.mercadolivre.com.br/MLB-3611964277-forro-da-tampa-traseira-hyundai-santa-fe-817512w000-1218-_JM",
    "category": "tampa",
    "subcategory": [
        "traseiro"
    ]
},
{
    "id": "MLB4476683176",
    "title": "Polia Do Virabrequim Gm Tracker / Cruze 1.8 (55565) (12/16) ",
    "value_name_brand": "GM",
    "value_name_model": "Modelo não especificado",
    "price": 700,
    "picture_ids": [
        "769858-MLB74797782341_022024",
        "730901-MLB74797723203_022024",
        "681338-MLB74798415855_022024"
    ],
    "permalink": "https://produto.mercadolivre.com.br/MLB-4476683176-polia-do-virabrequim-gm-tracker-cruze-18-55565-1216-_JM",
    "category": "outros",
    "subcategory": [
        "outros"
    ]
},
{
    "id": "MLB3325178487",
    "title": "Lanterna Traseira  Jetta 2012/ L. Esquerdo Fume Cód 6003tn0",
    "value_name_brand": "Volkswagen",
    "value_name_model": "Modelo não especificado",
    "price": 690,
    "picture_ids": [
        "951394-MLB69563246641_052023",
        "648929-MLB69549641272_052023",
        "787169-MLB69549787732_052023"
    ],
    "permalink": "https://produto.mercadolivre.com.br/MLB-3325178487-lanterna-traseira-jetta-2012-l-esquerdo-fume-cod-6003tn0-_JM",
    "category": "lanterna",
    "subcategory": [
        "esquerdo",
        "traseiro"
    ]
},
{
    "id": "MLB3415127163",
    "title": "Polaina Ponteira Traseira Lado Direita Saveiro G5 G6.",
    "value_name_brand": "Volkswagen",
    "value_name_model": "Saveiro",
    "price": 700,
    "picture_ids": [
        "966526-MLB71174087889_082023",
        "995867-MLB71134856074_082023",
        "661359-MLB71174127085_082023"
    ],
    "permalink": "https://produto.mercadolivre.com.br/MLB-3415127163-polaina-ponteira-traseira-lado-direita-saveiro-g5-g6-_JM",
    "category": "outros",
    "subcategory": [
        "direito",
        "traseiro"
    ]
},
{
    "id": "MLB3324609945",
    "title": "Lanterna Traseira Jac J3 Sedan Turin 2010/ L.esquerdo",
    "value_name_brand": "JAC",
    "value_name_model": "Modelo não especificado",
    "price": 690,
    "picture_ids": [
        "948238-MLB69550106303_052023",
        "951885-MLB69550020385_052023",
        "848127-MLB69536768010_052023"
    ],
    "permalink": "https://produto.mercadolivre.com.br/MLB-3324609945-lanterna-traseira-jac-j3-sedan-turin-2010-lesquerdo-_JM",
    "category": "lanterna",
    "subcategory": [
        "esquerdo",
        "traseiro"
    ]
},
{
    "id": "MLB3589234801",
    "title": "Comando Do Vidro Elétrico Fiat Toro Ranch 22 Lado Esquerdo ",
    "value_name_brand": "Fiat Mopar",
    "value_name_model": "Modelo não especificado",
    "price": 690,
    "picture_ids": [
        "985225-MLB74295846356_022024",
        "841811-MLB74295552046_022024",
        "762584-MLB74411283411_022024"
    ],
    "permalink": "https://produto.mercadolivre.com.br/MLB-3589234801-comando-do-vidro-eletrico-fiat-toro-ranch-22-lado-esquerdo-_JM",
    "category": "vidro",
    "subcategory": [
        "esquerdo"
    ]
},
{
    "id": "MLB3528607203",
    "title": " Luz De Cortesia Teto Porta Óculos Jetta 2011 2017 5c6867489",
    "value_name_brand": "Volkswagen",
    "value_name_model": "Modelo não especificado",
    "price": 680,
    "picture_ids": [
        "947022-MLB73110731056_122023",
        "858043-MLB73194575441_122023",
        "846916-MLB73110524256_122023"
    ],
    "permalink": "https://produto.mercadolivre.com.br/MLB-3528607203-luz-de-cortesia-teto-porta-oculos-jetta-2011-2017-5c6867489-_JM",
    "category": "porta",
    "subcategory": [
        "outros"
    ]
},
{
    "id": "MLB3402403683",
    "title": "Chave De Seta Limpador Jac J2 2012 A 2015.",
    "value_name_brand": "Jac Motors",
    "value_name_model": "Modelo não especificado",
    "price": 680,
    "picture_ids": [
        "718560-MLB70935619897_082023",
        "754807-MLB70901113432_082023",
        "846111-MLB70935667505_082023"
    ],
    "permalink": "https://produto.mercadolivre.com.br/MLB-3402403683-chave-de-seta-limpador-jac-j2-2012-a-2015-_JM",
    "category": "limpador",
    "subcategory": [
        "outros"
    ]
},
{
    "id": "MLB3680344074",
    "title": "Farol Uno  2016/ Máscara Negra Original Cód 51931729",
    "value_name_brand": "Fiat",
    "value_name_model": "Modelo não especificado",
    "price": 680,
    "picture_ids": [
        "997708-MLB69684763387_052023",
        "853358-MLB69685304877_052023",
        "713997-MLB69670286876_052023"
    ],
    "permalink": "https://produto.mercadolivre.com.br/MLB-3680344074-farol-uno-2016-mascara-negra-original-cod-51931729-_JM",
    "category": "farol",
    "subcategory": [
        "outros"
    ]
},
{
    "id": "MLB4120102808",
    "title": "Tampa Válvula Lifan X60 1.8 2014 A 2016",
    "value_name_brand": "Lifan",
    "value_name_model": "X60",
    "price": 680,
    "picture_ids": [
        "773094-MLB72181619622_102023",
        "781207-MLB72181619610_102023",
        "617582-MLB72243499255_102023"
    ],
    "permalink": "https://produto.mercadolivre.com.br/MLB-4120102808-tampa-valvula-lifan-x60-18-2014-a-2016-_JM",
    "category": "tampa",
    "subcategory": [
        "outros"
    ]
},
{
    "id": "MLB3445449269",
    "title": "Farol Toyota Corolla 2005/ L.direito Cromado Tyc ",
    "value_name_brand": "TYC",
    "value_name_model": "Modelo não especificado",
    "price": 680,
    "picture_ids": [
        "923071-MLB71721126369_092023",
        "611699-MLB71670288302_092023",
        "748996-MLB71670228724_092023"
    ],
    "permalink": "https://produto.mercadolivre.com.br/MLB-3445449269-farol-toyota-corolla-2005-ldireito-cromado-tyc-_JM",
    "category": "farol",
    "subcategory": [
        "direito"
    ]
},
{
    "id": "MLB3482151055",
    "title": "Par Dobradiça Braço Capo Ford Fusion 2014cód Ds73f16800",
    "value_name_brand": "Ford",
    "value_name_model": "Modelo não especificado",
    "price": 680,
    "picture_ids": [
        "841609-MLB72265509738_102023",
        "741979-MLB72329470149_102023",
        "779227-MLB72265895226_102023"
    ],
    "permalink": "https://produto.mercadolivre.com.br/MLB-3482151055-par-dobradica-braco-capo-ford-fusion-2014cod-ds73f16800-_JM",
    "category": "braço",
    "subcategory": [
        "outros"
    ]
},
{
    "id": "MLB3491232891",
    "title": "Porta Óculos E Luz De Cortesia Ranger 2013/ Cód Cn15a519a58",
    "value_name_brand": "Ford",
    "value_name_model": "Modelo não especificado",
    "price": 650,
    "picture_ids": [
        "757718-MLB72484519507_102023",
        "855747-MLB72484755873_102023",
        "664591-MLB72416671222_102023"
    ],
    "permalink": "https://produto.mercadolivre.com.br/MLB-3491232891-porta-oculos-e-luz-de-cortesia-ranger-2013-cod-cn15a519a58-_JM",
    "category": "porta",
    "subcategory": [
        "outros"
    ]
},
{
    "id": "MLB3902649938",
    "title": "Ponteira Pára-choque Traseiro Saveiro G4 Lado-e 2006 A 2010.",
    "value_name_brand": "Volkswagen",
    "value_name_model": "Modelo não especificado",
    "price": 650,
    "picture_ids": [
        "918263-MLB71084035112_082023",
        "843917-MLB71083839552_082023",
        "901832-MLB71122117225_082023"
    ],
    "permalink": "https://produto.mercadolivre.com.br/MLB-3902649938-ponteira-para-choque-traseiro-saveiro-g4-lado-e-2006-a-2010-_JM",
    "category": "outros",
    "subcategory": [
        "traseiro"
    ]
},
{
    "id": "MLB3329579379",
    "title": "Farol Renault Sandero 2007/11 Lado Direito Original",
    "value_name_brand": "Renault",
    "value_name_model": "Modelo não especificado",
    "price": 650,
    "picture_ids": [
        "697070-MLB69635930295_052023",
        "854422-MLB69635999519_052023",
        "792039-MLB69635999557_052023"
    ],
    "permalink": "https://produto.mercadolivre.com.br/MLB-3329579379-farol-renault-sandero-200711-lado-direito-original-_JM",
    "category": "farol",
    "subcategory": [
        "direito"
    ]
},
{
    "id": "MLB3713147362",
    "title": "Retrovisor Fiesta Titânio L-d 2015 A 2018 Elétrico Com/seta.",
    "value_name_brand": "Ford",
    "value_name_model": "Modelo não especificado",
    "price": 650,
    "picture_ids": [
        "910724-MLB69927574278_062023",
        "986509-MLB69946162495_062023",
        "831232-MLB69928065526_062023"
    ],
    "permalink": "https://produto.mercadolivre.com.br/MLB-3713147362-retrovisor-fiesta-titnio-l-d-2015-a-2018-eletrico-comseta-_JM",
    "category": "retrovisor",
    "subcategory": [
        "outros"
    ]
},
{
    "id": "MLB4433781026",
    "title": "Retrovisor Corolla Fielder 2003/08 Lado Esquerdo Original ",
    "value_name_brand": "Toyota",
    "value_name_model": "Modelo não especificado",
    "price": 650,
    "picture_ids": [
        "612327-MLB74323249572_022024",
        "984334-MLB74323259458_022024",
        "846722-MLB74323279034_022024"
    ],
    "permalink": "https://produto.mercadolivre.com.br/MLB-4433781026-retrovisor-corolla-fielder-200308-lado-esquerdo-original-_JM",
    "category": "retrovisor",
    "subcategory": [
        "esquerdo"
    ]
},
{
    "id": "MLB3715460796",
    "title": "Retrovisor Tucson L. Direito 2008/12 Elétrico S/seta 3 Pinos",
    "value_name_brand": "Hyundai",
    "value_name_model": "Modelo não especificado",
    "price": 650,
    "picture_ids": [
        "952074-MLB69960912045_062023",
        "931408-MLB69942531326_062023",
        "993779-MLB69960924195_062023"
    ],
    "permalink": "https://produto.mercadolivre.com.br/MLB-3715460796-retrovisor-tucson-l-direito-200812-eletrico-sseta-3-pinos-_JM",
    "category": "retrovisor",
    "subcategory": [
        "direito"
    ]
},
{
    "id": "MLB3358406705",
    "title": "Moldura Painel Central Amarok 2010 A 2016.",
    "value_name_brand": "Volkswagen",
    "value_name_model": "Amarok",
    "price": 650,
    "picture_ids": [
        "683831-MLB70156233563_062023",
        "906533-MLB70135784924_062023",
        "859410-MLB70135412940_062023"
    ],
    "permalink": "https://produto.mercadolivre.com.br/MLB-3358406705-moldura-painel-central-amarok-2010-a-2016-_JM",
    "category": "painel",
    "subcategory": [
        "outros"
    ]
},
{
    "id": "MLB3347246955",
    "title": "Retrovisor Sonic Lado Direito 2012 A 2015 Elétrico Sem/seta.",
    "value_name_brand": "GM",
    "value_name_model": "Modelo não especificado",
    "price": 650,
    "picture_ids": [
        "750756-MLB69963080685_062023",
        "974834-MLB69944765484_062023",
        "897166-MLB69962951213_062023"
    ],
    "permalink": "https://produto.mercadolivre.com.br/MLB-3347246955-retrovisor-sonic-lado-direito-2012-a-2015-eletrico-semseta-_JM",
    "category": "retrovisor",
    "subcategory": [
        "direito"
    ]
},
{
    "id": "MLB3477049753",
    "title": "Comando Vidros Elétrico Honda City 2016/l.esquerdo ",
    "value_name_brand": "Honda",
    "value_name_model": "Modelo não especificado",
    "price": 650,
    "picture_ids": [
        "763415-MLB72183122786_102023",
        "802722-MLB72183426518_102023",
        "719631-MLB72183426550_102023"
    ],
    "permalink": "https://produto.mercadolivre.com.br/MLB-3477049753-comando-vidros-eletrico-honda-city-2016lesquerdo-_JM",
    "category": "vidro",
    "subcategory": [
        "esquerdo"
    ]
},
{
    "id": "MLB3638614387",
    "title": "Botão Freio De Mão Elétrico Jeep Compass (2021) (735632247) ",
    "value_name_brand": "Jeep",
    "value_name_model": "Modelo não especificado",
    "price": 650,
    "picture_ids": [
        "825449-MLB75256048696_032024",
        "897727-MLB75405233403_032024",
        "724940-MLB75405637051_032024"
    ],
    "permalink": "https://produto.mercadolivre.com.br/MLB-3638614387-boto-freio-de-mo-eletrico-jeep-compass-2021-735632247-_JM",
    "category": "outros",
    "subcategory": [
        "outros"
    ]
},
{
    "id": "MLB4068876944",
    "title": "Condensador Ar Condicionado Fiat Stilo 1.8 Original Usado ",
    "value_name_brand": "Fiat",
    "value_name_model": "Modelo não especificado",
    "price": 650,
    "picture_ids": [
        "663022-MLB71915758053_092023",
        "754838-MLB71915758047_092023",
        "726552-MLB71915758059_092023"
    ],
    "permalink": "https://produto.mercadolivre.com.br/MLB-4068876944-condensador-ar-condicionado-fiat-stilo-18-original-usado-_JM",
    "category": "outros",
    "subcategory": [
        "outros"
    ]
},
{
    "id": "MLB4431660476",
    "title": "Suporte Farol Lado Direito Fiat Toro 2016 A 2023.",
    "value_name_brand": "Fiat",
    "value_name_model": "Modelo não especificado",
    "price": 650,
    "picture_ids": [
        "779003-MLB74426804565_022024",
        "764017-MLB74310460038_022024",
        "612199-MLB74310430362_022024"
    ],
    "permalink": "https://produto.mercadolivre.com.br/MLB-4431660476-suporte-farol-lado-direito-fiat-toro-2016-a-2023-_JM",
    "category": "farol",
    "subcategory": [
        "direito"
    ]
},
{
    "id": "MLB3326927337",
    "title": "Lanterna Nissan Sentra 2007/12 L.esquerdo  Tyc Cod 116220",
    "value_name_brand": "Nissan",
    "value_name_model": "Modelo não especificado",
    "price": 650,
    "picture_ids": [
        "725066-MLB69576720474_052023",
        "982469-MLB69576699174_052023",
        "870537-MLB69576729540_052023"
    ],
    "permalink": "https://produto.mercadolivre.com.br/MLB-3326927337-lanterna-nissan-sentra-200712-lesquerdo-tyc-cod-116220-_JM",
    "category": "lanterna",
    "subcategory": [
        "esquerdo"
    ]
},
{
    "id": "MLB3460214749",
    "title": "Radiador Agua Gm S10 Pitbul Original Usado ",
    "value_name_brand": "GM",
    "value_name_model": "Modelo não especificado",
    "price": 650,
    "picture_ids": [
        "629927-MLB71941335786_092023",
        "760455-MLB71996274151_092023",
        "919959-MLB71940623408_092023"
    ],
    "permalink": "https://produto.mercadolivre.com.br/MLB-3460214749-radiador-agua-gm-s10-pitbul-original-usado-_JM",
    "category": "radiador",
    "subcategory": [
        "outros"
    ]
},
{
    "id": "MLB3381827883",
    "title": "Caixa Filtro De Ar Corolla 1.8/2.0 2015 A 2018.",
    "value_name_brand": "Toyota",
    "value_name_model": "Modelo não especificado",
    "price": 630,
    "picture_ids": [
        "902002-MLB70582039077_072023",
        "977621-MLB70554313190_072023",
        "726183-MLB70554627030_072023"
    ],
    "permalink": "https://produto.mercadolivre.com.br/MLB-3381827883-caixa-filtro-de-ar-corolla-1820-2015-a-2018-_JM",
    "category": "caixa",
    "subcategory": [
        "outros"
    ]
},
{
    "id": "MLB4474260604",
    "title": "Tampa De Cobertura Do Motor Fiat Toro 2016/ Flex (original)",
    "value_name_brand": "Fiat",
    "value_name_model": "Modelo não especificado",
    "price": 600,
    "picture_ids": [
        "611299-MLB74774384531_022024",
        "675838-MLB74775127037_022024",
        "850973-MLB74774384541_022024"
    ],
    "permalink": "https://produto.mercadolivre.com.br/MLB-4474260604-tampa-de-cobertura-do-motor-fiat-toro-2016-flex-original-_JM",
    "category": "motor",
    "subcategory": [
        "outros"
    ]
},
{
    "id": "MLB3618795701",
    "title": "Retrovisor Gol G5 L.d 2 Portas Elétrico C/seta Orig 5 Fios ",
    "value_name_brand": "Volkswagen",
    "value_name_model": "Modelo não especificado",
    "price": 590,
    "picture_ids": [
        "631272-MLB74863118510_032024",
        "634099-MLB74862960854_032024",
        "850086-MLB74863020242_032024"
    ],
    "permalink": "https://produto.mercadolivre.com.br/MLB-3618795701-retrovisor-gol-g5-ld-2-portas-eletrico-cseta-orig-5-fios-_JM",
    "category": "retrovisor",
    "subcategory": [
        "outros"
    ]
},
{
    "id": "MLB3925093182",
    "title": "Aplique Moldura Traseira Lado Direito Ford Ranger 2005/2009",
    "value_name_brand": "Ford",
    "value_name_model": "Modelo não especificado",
    "price": 600,
    "picture_ids": [
        "948824-MLB71253900011_082023",
        "635158-MLB71213213064_082023",
        "979527-MLB71213014178_082023"
    ],
    "permalink": "https://produto.mercadolivre.com.br/MLB-3925093182-aplique-moldura-traseira-lado-direito-ford-ranger-20052009-_JM",
    "category": "moldura",
    "subcategory": [
        "direito",
        "traseiro"
    ]
},
{
    "id": "MLB4419332252",
    "title": "Portinhola Tanque Toro Ranch Diesel 2022/  Cód 51979575",
    "value_name_brand": "mopar Fiat",
    "value_name_model": "Modelo não especificado",
    "price": 600,
    "picture_ids": [
        "853694-MLB74347220037_022024",
        "727875-MLB74233148976_022024",
        "753173-MLB74233208684_022024"
    ],
    "permalink": "https://produto.mercadolivre.com.br/MLB-4419332252-portinhola-tanque-toro-ranch-diesel-2022-cod-51979575-_JM",
    "category": "portinhola",
    "subcategory": [
        "outros"
    ]
},
{
    "id": "MLB3376129605",
    "title": "Caixa Filtro De Ar New Fiesta 2014/ Código C1b19600be",
    "value_name_brand": "Ford",
    "value_name_model": "Modelo não especificado",
    "price": 590,
    "picture_ids": [
        "946020-MLB70458185598_072023",
        "889532-MLB70483549789_072023",
        "809024-MLB70483877501_072023"
    ],
    "permalink": "https://produto.mercadolivre.com.br/MLB-3376129605-caixa-filtro-de-ar-new-fiesta-2014-codigo-c1b19600be-_JM",
    "category": "caixa",
    "subcategory": [
        "outros"
    ]
},
{
    "id": "MLB3585935097",
    "title": "Moldura Do Painel  S10 Blazer 2006/ Código 93287901",
    "value_name_brand": "GM",
    "value_name_model": "S10",
    "price": 600,
    "picture_ids": [
        "943543-MLB74344503815_022024",
        "795864-MLB74345164895_022024",
        "711953-MLB74345144993_022024"
    ],
    "permalink": "https://produto.mercadolivre.com.br/MLB-3585935097-moldura-do-painel-s10-blazer-2006-codigo-93287901-_JM",
    "category": "painel",
    "subcategory": [
        "outros"
    ]
}
]